odoo10_addon_l10n_it_fatturapa_out_di-10.0.1.0.0.99.dev4-py3.8-nspkg.pth
odoo/addons/l10n_it_fatturapa_out_di/README.rst
odoo/addons/l10n_it_fatturapa_out_di/__init__.py
odoo/addons/l10n_it_fatturapa_out_di/__manifest__.py
odoo/addons/l10n_it_fatturapa_out_di/i18n/it.po
odoo/addons/l10n_it_fatturapa_out_di/i18n/l10n_it_fatturapa_out_di.pot
odoo/addons/l10n_it_fatturapa_out_di/readme/CONTRIBUTORS.rst
odoo/addons/l10n_it_fatturapa_out_di/readme/DESCRIPTION.rst
odoo/addons/l10n_it_fatturapa_out_di/static/description/icon.png
odoo/addons/l10n_it_fatturapa_out_di/static/description/index.html
odoo/addons/l10n_it_fatturapa_out_di/tests/__init__.py
odoo/addons/l10n_it_fatturapa_out_di/tests/test_fatturapa_xml_validation.py
odoo/addons/l10n_it_fatturapa_out_di/tests/data/IT06363391001_00001.xml
odoo/addons/l10n_it_fatturapa_out_di/tests/data/IT06363391001_00002.xml
odoo/addons/l10n_it_fatturapa_out_di/tests/data/IT06363391001_00003.xml
odoo/addons/l10n_it_fatturapa_out_di/wizard/__init__.py
odoo/addons/l10n_it_fatturapa_out_di/wizard/wizard_export_fatturapa.py
odoo10_addon_l10n_it_fatturapa_out_di-10.0.1.0.0.99.dev4.dist-info/METADATA
odoo10_addon_l10n_it_fatturapa_out_di-10.0.1.0.0.99.dev4.dist-info/WHEEL
odoo10_addon_l10n_it_fatturapa_out_di-10.0.1.0.0.99.dev4.dist-info/namespace_packages.txt
odoo10_addon_l10n_it_fatturapa_out_di-10.0.1.0.0.99.dev4.dist-info/top_level.txt
odoo10_addon_l10n_it_fatturapa_out_di-10.0.1.0.0.99.dev4.dist-info/RECORD
