Metadata-Version: 2.1
Name: odoo10-addon-l10n-it-fatturapa-out-di
Version: 10.0.1.0.0.99.dev4
Summary: Dichiarazioni d'intento in fatturapa
Home-page: https://github.com/OCA/l10n-italy
Author: Marco Colombo,Odoo Community Association (OCA)
Author-email: support@odoo-community.org
License: AGPL-3
Platform: UNKNOWN
Classifier: Programming Language :: Python
Classifier: Framework :: Odoo
Classifier: Framework :: Odoo :: 10.0
Classifier: License :: OSI Approved :: GNU Affero General Public License v3
Classifier: Development Status :: 3 - Alpha
Requires-Python: ~=2.7
Requires-Dist: odoo10-addon-l10n-it-dichiarazione-intento
Requires-Dist: odoo10-addon-l10n-it-fatturapa-out
Requires-Dist: odoo <10.1dev,>=10.0
